remerkleable/__init__.py
remerkleable/basic.py
remerkleable/bitfields.py
remerkleable/byte_arrays.py
remerkleable/complex.py
remerkleable/core.py
remerkleable/history.py
remerkleable/readonly_iters.py
remerkleable/settings.py
remerkleable/stable_container.py
remerkleable/subtree.py
remerkleable/test_arithmetic.py
remerkleable/test_impl.py
remerkleable/test_typing.py
remerkleable/tree.py
remerkleable/union.py
remerkleable/virtual.py
remerkleable-0.1.28.dist-info/LICENSE
remerkleable-0.1.28.dist-info/METADATA
remerkleable-0.1.28.dist-info/WHEEL
remerkleable-0.1.28.dist-info/top_level.txt
remerkleable-0.1.28.dist-info/RECORD
