Metadata-Version: 2.1
Name: remerkleable
Version: 0.1.28
Summary: Typed mutable SSZ views over cached and immutable binary merkle trees
Home-page: https://github.com/protolambda/remerkleable
Author: protolambda
Author-email: proto+pip@protolambda.com
License: MIT
Keywords: merkle,merkleize,merkle-tree,merkle-trie,trie,ssz,hash-tree-root,eth2
Classifier: Development Status :: 4 - Beta
Classifier: Intended Audience :: Developers
Classifier: License :: OSI Approved :: MIT License
Classifier: Natural Language :: English
Classifier: Programming Language :: Python :: 3
Classifier: Programming Language :: Python :: 3.8
Classifier: Programming Language :: Python :: Implementation :: PyPy
Classifier: Operating System :: OS Independent
Requires-Python: >=3.8, <4
License-File: LICENSE
Provides-Extra: docs
Requires-Dist: sphinx ; extra == 'docs'
Requires-Dist: sphinx-autodoc-typehints ; extra == 'docs'
Requires-Dist: pallets-sphinx-themes ; extra == 'docs'
Requires-Dist: sphinx-issues ; extra == 'docs'
Provides-Extra: linting
Requires-Dist: flake8 ; extra == 'linting'
Provides-Extra: testing
Requires-Dist: pytest ; extra == 'testing'
